hfendpoint/__init__.py
hfendpoint/hf_endpoint.py
hfendpoint-1.0.4.dist-info/LICENSE
hfendpoint-1.0.4.dist-info/METADATA
hfendpoint-1.0.4.dist-info/WHEEL
hfendpoint-1.0.4.dist-info/top_level.txt
hfendpoint-1.0.4.dist-info/RECORD
