Metadata-Version: 2.1
Name: hfendpoint
Version: 1.0.4
Summary: A package that sets up a local API Endpoint for a model from the HuggingFace Model Hub.
Home-page: https://github.com/Solonce/HFEndpoint
Author: Solomon Ince
Author-email: sollyince@gmail.com
Project-URL: Bug Tracker, https://github.com/Solonce/HFEndpoint/issues
Classifier: Programming Language :: Python :: 3
Classifier: License :: OSI Approved :: MIT License
Classifier: Operating System :: OS Independent
Requires-Python: >=3.6
License-File: LICENSE
